cli.py
src/cimaclub-dl_oubaydos/index.py
src/cimaclub-dl_oubaydos/logger.py
src/cimaclub-dl_oubaydos/model.py
cimaclub-0.0.1.dist-info/METADATA
cimaclub-0.0.1.dist-info/WHEEL
cimaclub-0.0.1.dist-info/licenses/LICENSE
cimaclub-0.0.1.dist-info/RECORD
