Metadata-Version: 2.1
Name: cimaclub
Version: 0.0.1
Summary: movies and series downloader though cimaclub
Project-URL: Homepage, https://github.com/oubaydos/cimaclub-dl
Project-URL: Bug Tracker, https://github.com/oubaydos/cimaclub-dl/issues
Author-email: obaydah bouifadene <oubaydos@gmail.com>
License: MIT License
Classifier: License :: OSI Approved :: MIT License
Classifier: Operating System :: OS Independent
Classifier: Programming Language :: Python :: 3
Requires-Python: >=3.7
Requires-Dist: beautifulsoup4==4.10.0
Requires-Dist: requests==2.26.0
